COPYING
MANIFEST.in
README.rst
setup.py
docs/contributing.rst
docs/done.rst
docs/library.rst
docs/overview.rst
docs/rope.rst
docs/dev/issues.rst
docs/dev/todo.rst
rope/__init__.py
rope/base/__init__.py
rope/base/arguments.py
rope/base/ast.py
rope/base/astutils.py
rope/base/builtins.py
rope/base/change.py
rope/base/codeanalyze.py
rope/base/default_config.py
rope/base/evaluate.py
rope/base/exceptions.py
rope/base/fscommands.py
rope/base/history.py
rope/base/libutils.py
rope/base/prefs.py
rope/base/project.py
rope/base/pycore.py
rope/base/pynames.py
rope/base/pynamesdef.py
rope/base/pyobjects.py
rope/base/pyobjectsdef.py
rope/base/pyscopes.py
rope/base/resourceobserver.py
rope/base/resources.py
rope/base/simplify.py
rope/base/stdmods.py
rope/base/taskhandle.py
rope/base/worder.py
rope/base/oi/__init__.py
rope/base/oi/doa.py
rope/base/oi/memorydb.py
rope/base/oi/objectdb.py
rope/base/oi/objectinfo.py
rope/base/oi/runmod.py
rope/base/oi/soa.py
rope/base/oi/soi.py
rope/base/oi/transform.py
rope/base/oi/type_hinting/__init__.py
rope/base/oi/type_hinting/evaluate.py
rope/base/oi/type_hinting/factory.py
rope/base/oi/type_hinting/interfaces.py
rope/base/oi/type_hinting/utils.py
rope/base/oi/type_hinting/providers/__init__.py
rope/base/oi/type_hinting/providers/composite.py
rope/base/oi/type_hinting/providers/docstrings.py
rope/base/oi/type_hinting/providers/inheritance.py
rope/base/oi/type_hinting/providers/interfaces.py
rope/base/oi/type_hinting/providers/numpydocstrings.py
rope/base/oi/type_hinting/providers/pep0484_type_comments.py
rope/base/oi/type_hinting/resolvers/__init__.py
rope/base/oi/type_hinting/resolvers/composite.py
rope/base/oi/type_hinting/resolvers/interfaces.py
rope/base/oi/type_hinting/resolvers/types.py
rope/base/utils/__init__.py
rope/base/utils/datastructures.py
rope/base/utils/pycompat.py
rope/contrib/__init__.py
rope/contrib/autoimport.py
rope/contrib/changestack.py
rope/contrib/codeassist.py
rope/contrib/finderrors.py
rope/contrib/findit.py
ropee.egg-info/PKG-INFO
ropee.egg-info/SOURCES.txt
ropee.egg-info/dependency_links.txt
ropee.egg-info/top_level.txt
